jsonflattifier/__init__.py
jsonflattifier/__main__.py
jsonflattifier/apis.py
jsonflattifier/errors.py
jsonflattifier/helpers.py
jsonflattifier/main.py
jsonflattifier/version.py
jsonflattifier-1.1.6.dist-info/LICENSE
jsonflattifier-1.1.6.dist-info/METADATA
jsonflattifier-1.1.6.dist-info/WHEEL
jsonflattifier-1.1.6.dist-info/top_level.txt
jsonflattifier-1.1.6.dist-info/RECORD
