Metadata-Version: 2.1
Name: jsonflattifier
Version: 1.1.6
Summary: Converts a JSON Document with nested objects and their parameters to the JSON Document with Flat Denormalised Data.
Home-page: https://gitlab.com/v.grigoryevskiy/json-flattifier
Author: Valentin Grigoryevskiy
Author-email: v.grigoryevskiy@gmail.com
License: MIT
Project-URL: Source, https://gitlab.com/v.grigoryevskiy/json-flattifier
Project-URL: Tracker, https://gitlab.com/v.grigoryevskiy/json-flattifier/issues
Keywords: json csv flat flattify flatten table convert denormalise combinations
Platform: UNKNOWN
Classifier: Development Status :: 4 - Beta
Classifier: Programming Language :: Python :: 3
Classifier: License :: OSI Approved :: MIT License
Classifier: Operating System :: OS Independent
Requires-Python: >=3.6
Requires-Dist: terminaltables
